c7n_kube/__init__.py
c7n_kube/cli.py
c7n_kube/client.py
c7n_kube/entry.py
c7n_kube/exceptions.py
c7n_kube/filters.py
c7n_kube/policy.py
c7n_kube/provider.py
c7n_kube/query.py
c7n_kube/server.py
c7n_kube/utils.py
c7n_kube/actions/__init__.py
c7n_kube/actions/core.py
c7n_kube/actions/labels.py
c7n_kube/actions/shared.py
c7n_kube/resources/__init__.py
c7n_kube/resources/crd.py
c7n_kube/resources/resource_map.py
c7n_kube/resources/apps/__init__.py
c7n_kube/resources/apps/daemonset.py
c7n_kube/resources/apps/deployment.py
c7n_kube/resources/apps/replicaset.py
c7n_kube/resources/apps/statefulset.py
c7n_kube/resources/core/__init__.py
c7n_kube/resources/core/configmap.py
c7n_kube/resources/core/namespace.py
c7n_kube/resources/core/node.py
c7n_kube/resources/core/pod.py
c7n_kube/resources/core/replicationcontroller.py
c7n_kube/resources/core/secret.py
c7n_kube/resources/core/service.py
c7n_kube/resources/core/serviceaccount.py
c7n_kube/resources/core/volume.py
c7n_kube/resources/rbac/role.py
c7n_kube-0.2.48.dist-info/METADATA
c7n_kube-0.2.48.dist-info/WHEEL
c7n_kube-0.2.48.dist-info/entry_points.txt
c7n_kube-0.2.48.dist-info/RECORD
