Metadata-Version: 2.4
Name: c7n_kube
Version: 0.2.48
Summary: Cloud Custodian - Kubernetes Provider
Project-URL: homepage, https://cloudcustodian.io
Project-URL: repository, https://github.com/cloud-custodian/cloud-custodian
Project-URL: documentation, https://cloudcustodian.io/docs/
Author: Cloud Custodian Project
License-Expression: Apache-2.0
Classifier: License :: OSI Approved :: Apache Software License
Classifier: Topic :: System :: Distributed Computing
Classifier: Topic :: System :: Systems Administration
Requires-Python: <4.0.0,>=3.9.2
Requires-Dist: c7n ==0.9.49
Requires-Dist: jsonpatch ==1.33
Requires-Dist: kubernetes ==33.1.0
